[
    {
        "character": "䍂",
        "variants": [],
        "synonyms": [
            "𦈣"
        ],
        "definitions": [],
        "special_entries": []
    },
    {
        "character": "䍃",
        "variants": [],
        "synonyms": [],
        "definitions": [
            {
                "type": "single_sound_single_meaning",
                "pinyin": "yóu",
                "rhyme_book": "《廣韻》以周切，平尤以。宵部。",
                "meanings": [
                    "瓮瓶一类的瓦器"
                ]
            }
        ],
        "special_entries": []
    },
    {
        "character": "䍄",
        "variants": [],
        "synonyms": [],
        "definitions": [
            {
                "type": "single_sound_single_meaning",
                "pinyin": "diǎn",
                "rhyme_book": "《廣韻》多忝切，上忝端。談部。",
                "meanings": [
                    "瓦器缺损"
                ]
            }
        ],
        "special_entries": []
    },
    {
        "character": "䍅",
        "variants": [],
        "synonyms": [
            "𦉢"
        ],
        "definitions": [],
        "special_entries": []
    },
    {
        "character": "䍆",
        "variants": [],
        "synonyms": [
            "𤲑"
        ],
        "definitions": [],
        "special_entries": []
    },
    {
        "character": "䍇",
        "variants": [],
        "synonyms": [],
        "definitions": [
            {
                "type": "single_sound_single_meaning",
                "pinyin": "tà",
                "rhyme_book": "《廣韻》徒盍切，入盍定。盍部。",
                "meanings": [
                    "平底缶"
                ]
            }
        ],
        "special_entries": []
    },
    {
        "character": "䍈",
        "variants": [],
        "synonyms": [
            "缾（瓶）"
        ],
        "definitions": [],
        "special_entries": []
    },
    {
        "character": "䍉",
        "variants": [],
        "synonyms": [],
        "definitions": [
            {
                "type": "single_sound_single_meaning",
                "pinyin": "䍉zhǎi",
                "rhyme_book": "《集韻》知駭切，上駭知。",
                "meanings": [
                    "残缺损伤的痕迹"
                ]
            }
        ],
        "special_entries": []
    },
    {
        "character": "䍊",
        "variants": [],
        "synonyms": [],
        "definitions": [
            {
                "type": "single_sound_single_meaning",
                "pinyin": "䍊jiāo",
                "rhyme_book": "《廣韻》古肴切，平肴見。又苦擊切。",
                "meanings": [
                    "古代土制的埙一类的吹奏乐器"
                ]
            }
        ],
        "special_entries": []
    },
    {
        "character": "䍋",
        "variants": [],
        "synonyms": [
            "𦉈"
        ],
        "definitions": [],
        "special_entries": []
    },
    {
        "character": "䍌",
        "variants": [],
        "synonyms": [
            "瓿"
        ],
        "definitions": [],
        "special_entries": []
    },
    {
        "character": "䍍",
        "variants": [],
        "synonyms": [],
        "definitions": [
            {
                "type": "single_sound_single_meaning",
                "pinyin": "kòu",
                "rhyme_book": "《廣韻》苦候切，去候溪。又空谷切。屋部。",
                "meanings": [
                    "没有烧过的砖瓦、陶器等的坯"
                ]
            }
        ],
        "special_entries": []
    },
    {
        "character": "䍎",
        "variants": [],
        "synonyms": [],
        "definitions": [
            {
                "type": "multi_sound_single_meaning",
                "pinyin": "cùn",
                "rhyme_book": "《廣韻》倉困切，去慁清。又倉甸切。諄部。",
                "meanings": [
                    "纺锤"
                ]
            },
            {
                "type": "multi_sound_single_meaning",
                "pinyin": "xiǎn",
                "rhyme_book": "《集韻》穌典切，上銑心。",
                "meanings": [
                    "小缶"
                ]
            }
        ],
        "special_entries": []
    },
    {
        "character": "缶",
        "variants": [],
        "synonyms": [],
        "definitions": [
            {
                "type": "single_sound_multi_meaning",
                "pinyin": "fǒu",
                "rhyme_book": "《廣韻》方久切，上有非。幽部。",
                "meanings": [
                    "盛酒浆的瓦器",
                    "古代一种瓦质打击乐器",
                    "量词"
                ]
            }
        ],
        "special_entries": []
    },
    {
        "character": "缷",
        "variants": [],
        "synonyms": [
            "卸"
        ],
        "definitions": [],
        "special_entries": []
    },
    {
        "character": "缸",
        "variants": [],
        "synonyms": [],
        "definitions": [
            {
                "type": "single_sound_multi_meaning",
                "pinyin": "gāng",
                "rhyme_book": "《廣韻》下江切，平江匣。又",
                "meanings": [
                    "古代陶制容器",
                    "用陶、瓷、搪瓷、玻璃等制的容器",
                    "像缸的器物",
                    "油灯；灯盏",
                    "缸瓦，用沙子、陶土等混合而成的一种质料"
                ]
            }
        ],
        "special_entries": []
    },
    {
        "character": "缹",
        "variants": [],
        "synonyms": [],
        "definitions": [
            {
                "type": "single_sound_single_meaning",
                "pinyin": "缹fǒu",
                "rhyme_book": "《廣韻》方久切，上有非。",
                "meanings": [
                    "蒸煮"
                ]
            }
        ],
        "special_entries": []
    },
    {
        "character": "缺",
        "variants": [],
        "synonyms": [],
        "definitions": [
            {
                "type": "multi_sound_multi_meaning",
                "pinyin": "quē",
                "rhyme_book": "《廣韻》苦穴切，入屑溪。又傾雪切。月部。",
                "meanings": [
                    "破损；残缺",
                    "缺口",
                    "缺陷；过失",
                    "不足；缺少",
                    "衰微；废弃",
                    "旧指官职的空额，后亦泛指一般职务的空额",
                    "该到未到"
                ]
            },
            {
                "type": "multi_sound_single_meaning",
                "pinyin": "kuǐ",
                "rhyme_book": "《集韻》犬繠切，上紙溪。支部。",
                "meanings": []
            }
        ],
        "special_entries": []
    },
    {
        "character": "缻",
        "variants": [],
        "synonyms": [
            "缶"
        ],
        "definitions": [],
        "special_entries": []
    },
    {
        "character": "缼",
        "variants": [],
        "synonyms": [
            "欠"
        ],
        "definitions": [],
        "special_entries": []
    },
    {
        "character": "缽",
        "variants": [],
        "synonyms": [
            "鉢"
        ],
        "definitions": [],
        "special_entries": []
    },
    {
        "character": "缾",
        "variants": [],
        "synonyms": [
            "瓶"
        ],
        "definitions": [],
        "special_entries": []
    },
    {
        "character": "缿",
        "variants": [],
        "synonyms": [],
        "definitions": [
            {
                "type": "single_sound_multi_meaning",
                "pinyin": "xiàng",
                "rhyme_book": "《廣韻》胡講切，上講匣。東部。",
                "meanings": [
                    "古代的储钱器，陶制或竹制，小口，可入而不可取出，类似后来的扑满或钱筒",
                    "古代接受告密文书的器具"
                ]
            }
        ],
        "special_entries": []
    },
    {
        "character": "罁",
        "variants": [],
        "synonyms": [],
        "definitions": [
            {
                "type": "single_sound_multi_meaning",
                "pinyin": "gāng",
                "rhyme_book": "《集韻》居郎切，平唐見。",
                "meanings": []
            }
        ],
        "special_entries": []
    },
    {
        "character": "罂",
        "variants": [
            "罂“罌”"
        ],
        "synonyms": [],
        "definitions": [],
        "special_entries": []
    },
    {
        "character": "罃",
        "variants": [],
        "synonyms": [],
        "definitions": [
            {
                "type": "single_sound_multi_meaning",
                "pinyin": "yīng",
                "rhyme_book": "《廣韻》烏莖切，平耕影。耕部。",
                "meanings": [
                    "古代盛灯油的油壶"
                ]
            }
        ],
        "special_entries": []
    },
    {
        "character": "罄",
        "variants": [],
        "synonyms": [],
        "definitions": [
            {
                "type": "single_sound_multi_meaning",
                "pinyin": "qìng",
                "rhyme_book": "《廣韻》苦定切，去徑溪。耕部。",
                "meanings": [
                    "器中空",
                    "尽；用尽",
                    "严整",
                    "现，出现"
                ]
            }
        ],
        "special_entries": []
    },
    {
        "character": "罅",
        "variants": [],
        "synonyms": [],
        "definitions": [
            {
                "type": "single_sound_multi_meaning",
                "pinyin": "xià",
                "rhyme_book": "《廣韻》呼訝切，去禡曉。魚部。",
                "meanings": [
                    "裂，裂开",
                    "裂缝；缝隙",
                    "漏洞；缺陷"
                ]
            }
        ],
        "special_entries": []
    },
    {
        "character": "罆",
        "variants": [],
        "synonyms": [
            "罐"
        ],
        "definitions": [],
        "special_entries": []
    },
    {
        "character": "罇",
        "variants": [],
        "synonyms": [],
        "definitions": [
            {
                "type": "single_sound_multi_meaning",
                "pinyin": "zūn",
                "rhyme_book": "《廣韻》祖昆切，平魂精。諄部。",
                "meanings": [
                    "姓"
                ]
            }
        ],
        "special_entries": []
    },
    {
        "character": "罈",
        "variants": [],
        "synonyms": [
            "罎（壜）"
        ],
        "definitions": [],
        "special_entries": []
    },
    {
        "character": "罊",
        "variants": [],
        "synonyms": [],
        "definitions": [
            {
                "type": "single_sound_single_meaning",
                "pinyin": "qì",
                "rhyme_book": "《廣韻》苦計切，去霽溪。又楷革切。錫部。",
                "meanings": [
                    "尽，器中尽"
                ]
            }
        ],
        "special_entries": []
    },
    {
        "character": "罋",
        "variants": [],
        "synonyms": [
            "瓮"
        ],
        "definitions": [],
        "special_entries": []
    },
    {
        "character": "罌",
        "variants": [],
        "synonyms": [],
        "definitions": [
            {
                "type": "single_sound_single_meaning",
                "pinyin": "yīng",
                "rhyme_book": "《廣韻》烏莖切，平耕影。耕部。",
                "meanings": [
                    "瓶一类的容器，比缶大，腹大口小"
                ]
            }
        ],
        "special_entries": []
    },
    {
        "character": "罍",
        "variants": [],
        "synonyms": [],
        "definitions": [
            {
                "type": "single_sound_multi_meaning",
                "pinyin": "léi",
                "rhyme_book": "《廣韻》魯回切，平灰來。微部。",
                "meanings": [
                    "古代一种盛酒的容器"
                ]
            }
        ],
        "special_entries": []
    },
    {
        "character": "罎",
        "variants": [],
        "synonyms": [
            "壜"
        ],
        "definitions": [],
        "special_entries": []
    },
    {
        "character": "罏",
        "variants": [],
        "synonyms": [],
        "definitions": [
            {
                "type": "single_sound_multi_meaning",
                "pinyin": "ú",
                "rhyme_book": "《廣韻》落胡切，平模來。魚部。",
                "meanings": [
                    "炉子"
                ]
            }
        ],
        "special_entries": []
    },
    {
        "character": "罐",
        "variants": [],
        "synonyms": [],
        "definitions": [
            {
                "type": "single_sound_multi_meaning",
                "pinyin": "guàn",
                "rhyme_book": "《集韻》古玩切，去换見。元部。",
                "meanings": [
                    "用陶或金属制造的盛物、汲水或烹煮用的圆筒形器物",
                    "指封装食品或其他物品的圆筒形容器",
                    "煤矿装煤用的斗车"
                ]
            }
        ],
        "special_entries": []
    },
    {
        "character": "𤕁",
        "variants": [],
        "synonyms": [],
        "definitions": [],
        "special_entries": [
            "\n𤕁音义未详。《字彙補·缶部》：“𤕁，出《穆天子傳》。音未詳。”《穆天子傳》卷四：“𠍝𤕁𠢮𦉔，珌佩百隻。”\n\n\n"
        ]
    },
    {
        "character": "𤫡",
        "variants": [],
        "synonyms": [
            "罌"
        ],
        "definitions": [],
        "special_entries": []
    },
    {
        "character": "𦈢",
        "variants": [],
        "synonyms": [
            "缶"
        ],
        "definitions": [],
        "special_entries": []
    },
    {
        "character": "𦈣",
        "variants": [],
        "synonyms": [],
        "definitions": [
            {
                "type": "single_sound_single_meaning",
                "pinyin": "𦈣yú",
                "rhyme_book": "《集韻》雲俱切，平虞云。",
                "meanings": [
                    "汲器"
                ]
            }
        ],
        "special_entries": []
    },
    {
        "character": "𦈤",
        "variants": [],
        "synonyms": [],
        "definitions": [
            {
                "type": "single_sound_single_meaning",
                "pinyin": "𦈤xiòng",
                "rhyme_book": "《龍龕手鑑》呼貢反。",
                "meanings": [
                    "孔𦈤"
                ]
            }
        ],
        "special_entries": []
    },
    {
        "character": "𦈦",
        "variants": [],
        "synonyms": [],
        "definitions": [
            {
                "type": "single_sound_single_meaning",
                "pinyin": "𦈦qì",
                "rhyme_book": "《改併四聲篇海》引",
                "meanings": [
                    "《龍龕手鑑》音棄",
                    "吹火"
                ]
            }
        ],
        "special_entries": []
    },
    {
        "character": "𦈧",
        "variants": [],
        "synonyms": [
            "桮（杯）"
        ],
        "definitions": [],
        "special_entries": []
    },
    {
        "character": "𦈨",
        "variants": [],
        "synonyms": [
            "鈃（銒）"
        ],
        "definitions": [],
        "special_entries": []
    },
    {
        "character": "𦈩",
        "variants": [],
        "synonyms": [],
        "definitions": [
            {
                "type": "single_sound_single_meaning",
                "pinyin": "⁵𦈩gǒng",
                "rhyme_book": "《改併四聲篇海》引",
                "meanings": [
                    "《餘文》古勇切",
                    "缻"
                ]
            }
        ],
        "special_entries": []
    },
    {
        "character": "𦈪",
        "variants": [],
        "synonyms": [
            "缻"
        ],
        "definitions": [],
        "special_entries": []
    },
    {
        "character": "𦈫",
        "variants": [],
        "synonyms": [
            "缺"
        ],
        "definitions": [],
        "special_entries": []
    },
    {
        "character": "𦈬",
        "variants": [],
        "synonyms": [],
        "definitions": [
            {
                "type": "single_sound_single_meaning",
                "pinyin": "𦈬zuǐ",
                "rhyme_book": "《改併四聲篇海》引",
                "meanings": [
                    "《龍龕手鑑》子累切",
                    "瓶𦈬"
                ]
            }
        ],
        "special_entries": []
    },
    {
        "character": "𦈭",
        "variants": [],
        "synonyms": [
            "越"
        ],
        "definitions": [],
        "special_entries": []
    },
    {
        "character": "𦈮",
        "variants": [],
        "synonyms": [
            "䍇"
        ],
        "definitions": [],
        "special_entries": []
    },
    {
        "character": "𦈯",
        "variants": [],
        "synonyms": [
            "器"
        ],
        "definitions": [],
        "special_entries": []
    },
    {
        "character": "𦈰",
        "variants": [],
        "synonyms": [],
        "definitions": [
            {
                "type": "single_sound_single_meaning",
                "pinyin": "⁶𦈰jiē",
                "rhyme_book": "《玉篇》革鞋切。",
                "meanings": [
                    "器好"
                ]
            }
        ],
        "special_entries": []
    },
    {
        "character": "𦈱",
        "variants": [],
        "synonyms": [
            "瓷"
        ],
        "definitions": [],
        "special_entries": []
    },
    {
        "character": "𦈲",
        "variants": [],
        "synonyms": [],
        "definitions": [
            {
                "type": "multi_sound_single_meaning",
                "pinyin": "kāi",
                "rhyme_book": "《集韻》丘哀切，平咍溪。",
                "meanings": [
                    "器名"
                ]
            },
            {
                "type": "multi_sound_single_meaning",
                "pinyin": "qǔ",
                "rhyme_book": "《字彙》丘舉切。",
                "meanings": [
                    "藏"
                ]
            }
        ],
        "special_entries": []
    },
    {
        "character": "𦈴",
        "variants": [],
        "synonyms": [
            "䍍"
        ],
        "definitions": [],
        "special_entries": []
    },
    {
        "character": "𦈵",
        "variants": [],
        "synonyms": [
            "鈃（銒）"
        ],
        "definitions": [],
        "special_entries": []
    },
    {
        "character": "𦈶",
        "variants": [],
        "synonyms": [],
        "definitions": [
            {
                "type": "single_sound_multi_meaning",
                "pinyin": "𦈶bēi",
                "rhyme_book": "《集韻》晡枚切，平灰幫。",
                "meanings": [
                    "缶"
                ]
            }
        ],
        "special_entries": []
    },
    {
        "character": "𦈷",
        "variants": [],
        "synonyms": [],
        "definitions": [
            {
                "type": "single_sound_single_meaning",
                "pinyin": "𦈷shū",
                "rhyme_book": "《龍龕手鑑·缶部》：“𦈷，音疏。”",
                "meanings": []
            }
        ],
        "special_entries": []
    },
    {
        "character": "𦈸",
        "variants": [],
        "synonyms": [],
        "definitions": [
            {
                "type": "single_sound_single_meaning",
                "pinyin": "yù",
                "rhyme_book": "《廣韻》雨逼切，入職云。職部。",
                "meanings": [
                    "瓦器"
                ]
            }
        ],
        "special_entries": []
    },
    {
        "character": "𦈹",
        "variants": [],
        "synonyms": [
            "瓽"
        ],
        "definitions": [],
        "special_entries": []
    },
    {
        "character": "𦈺",
        "variants": [],
        "synonyms": [],
        "definitions": [
            {
                "type": "single_sound_single_meaning",
                "pinyin": "𦈺zhǒu",
                "rhyme_book": "《玉篇》音帚。",
                "meanings": [
                    "器；器成"
                ]
            }
        ],
        "special_entries": []
    },
    {
        "character": "𦈻",
        "variants": [],
        "synonyms": [
            "琖（盞）"
        ],
        "definitions": [],
        "special_entries": []
    },
    {
        "character": "𦈼",
        "variants": [],
        "synonyms": [
            "𦉈"
        ],
        "definitions": [],
        "special_entries": []
    },
    {
        "character": "𦉁",
        "variants": [],
        "synonyms": [
            "㼵"
        ],
        "definitions": [],
        "special_entries": []
    },
    {
        "character": "𦉂",
        "variants": [],
        "synonyms": [
            "鍾"
        ],
        "definitions": [],
        "special_entries": []
    },
    {
        "character": "𦉆",
        "variants": [],
        "synonyms": [
            "碴"
        ],
        "definitions": [],
        "special_entries": []
    },
    {
        "character": "𦉇",
        "variants": [],
        "synonyms": [
            "缾（瓶）"
        ],
        "definitions": [],
        "special_entries": []
    },
    {
        "character": "𦉈",
        "variants": [],
        "synonyms": [],
        "definitions": [
            {
                "type": "single_sound_single_meaning",
                "pinyin": "chuí",
                "rhyme_book": "《廣韻》是為切，平支禪。歌部。",
                "meanings": [
                    "小口瓮"
                ]
            }
        ],
        "special_entries": []
    },
    {
        "character": "𦉉",
        "variants": [],
        "synonyms": [],
        "definitions": [
            {
                "type": "single_sound_single_meaning",
                "pinyin": "𦉉liù",
                "rhyme_book": "《改併四聲篇海》引",
                "meanings": [
                    "《餘文》力救切",
                    "甑"
                ]
            }
        ],
        "special_entries": []
    },
    {
        "character": "𦉍",
        "variants": [],
        "synonyms": [
            "罌"
        ],
        "definitions": [],
        "special_entries": []
    },
    {
        "character": "𦉎",
        "variants": [],
        "synonyms": [],
        "definitions": [
            {
                "type": "single_sound_single_meaning",
                "pinyin": "𦉎suī",
                "rhyme_book": "《集韻》穌回切，平灰心。",
                "meanings": [
                    "瓦器名"
                ]
            }
        ],
        "special_entries": []
    },
    {
        "character": "𦉏",
        "variants": [],
        "synonyms": [
            "罅"
        ],
        "definitions": [],
        "special_entries": []
    },
    {
        "character": "𦉐",
        "variants": [],
        "synonyms": [],
        "definitions": [
            {
                "type": "single_sound_single_meaning",
                "pinyin": "𦉐zhǔ",
                "rhyme_book": "《改併四聲篇海》引",
                "meanings": [
                    "《龍龕手鑑》章吕切",
                    "盛米"
                ]
            }
        ],
        "special_entries": []
    },
    {
        "character": "𦉔",
        "variants": [],
        "synonyms": [],
        "definitions": [],
        "special_entries": [
            "\n𦉔音义未详。《穆天子傳》卷四：“𠍝𤕁𠢮𦉔，珌佩百隻。”\n\n\n"
        ]
    },
    {
        "character": "𦉕",
        "variants": [],
        "synonyms": [
            "𤮜"
        ],
        "definitions": [],
        "special_entries": []
    },
    {
        "character": "𦉖",
        "variants": [],
        "synonyms": [
            "𦈼（𦉈）"
        ],
        "definitions": [],
        "special_entries": []
    },
    {
        "character": "𦉙",
        "variants": [],
        "synonyms": [],
        "definitions": [
            {
                "type": "single_sound_multi_meaning",
                "pinyin": "biàn",
                "rhyme_book": "《集韻》婢典切，上銑並。",
                "meanings": [
                    "小缶",
                    "纺锤"
                ]
            }
        ],
        "special_entries": []
    },
    {
        "character": "𦉚",
        "variants": [],
        "synonyms": [
            "鬱"
        ],
        "definitions": [],
        "special_entries": []
    },
    {
        "character": "𦉜",
        "variants": [],
        "synonyms": [
            "甔"
        ],
        "definitions": [],
        "special_entries": []
    },
    {
        "character": "𦉝",
        "variants": [],
        "synonyms": [],
        "definitions": [
            {
                "type": "single_sound_single_meaning",
                "pinyin": "𦉝xìn",
                "rhyme_book": "《集韻》許慎切，去稕曉。",
                "meanings": [
                    "瓦器坼裂"
                ]
            }
        ],
        "special_entries": []
    },
    {
        "character": "𦉞",
        "variants": [],
        "synonyms": [
            "㽉"
        ],
        "definitions": [],
        "special_entries": []
    },
    {
        "character": "𦉟",
        "variants": [],
        "synonyms": [],
        "definitions": [
            {
                "type": "single_sound_single_meaning",
                "pinyin": "¹⁵𦉟yà",
                "rhyme_book": "《集韻》牛轄切，入鎋疑。",
                "meanings": [
                    "器皿缺损"
                ]
            }
        ],
        "special_entries": []
    },
    {
        "character": "𦉠",
        "variants": [
            "“𦉚”"
        ],
        "synonyms": [],
        "definitions": [],
        "special_entries": []
    },
    {
        "character": "𦉢",
        "variants": [],
        "synonyms": [],
        "definitions": [
            {
                "type": "single_sound_single_meaning",
                "pinyin": "líng",
                "rhyme_book": "《廣韻》郎丁切，平青來。耕部。",
                "meanings": [
                    "古代盛酒或水的容器，瓦制或青铜制"
                ]
            }
        ],
        "special_entries": []
    },
    {
        "character": "𦉣",
        "variants": [],
        "synonyms": [
            "𦉢"
        ],
        "definitions": [],
        "special_entries": []
    },
    {
        "character": "𦉥",
        "variants": [],
        "synonyms": [
            "瓮"
        ],
        "definitions": [],
        "special_entries": []
    },
    {
        "character": "𦉧",
        "variants": [],
        "synonyms": [],
        "definitions": [
            {
                "type": "single_sound_multi_meaning",
                "pinyin": "⁰𦉧yà",
                "rhyme_book": "《玉篇》五鎋切。",
                "meanings": [
                    "缺",
                    "缶属"
                ]
            }
        ],
        "special_entries": []
    },
    {
        "character": "𦉨",
        "variants": [],
        "synonyms": [],
        "definitions": [
            {
                "type": "single_sound_multi_meaning",
                "pinyin": "鑞g",
                "rhyme_book": null,
                "meanings": [
                    "瓶"
                ]
            }
        ],
        "special_entries": []
    },
    {
        "character": "𦉩",
        "variants": [],
        "synonyms": [
            "罍"
        ],
        "definitions": [],
        "special_entries": []
    },
    {
        "character": "𬙎",
        "variants": [
            "𬙎“罏”"
        ],
        "synonyms": [],
        "definitions": [],
        "special_entries": []
    }
]