[
    {
        "character": "㸝",
        "variants": [],
        "synonyms": [],
        "definitions": [
            {
                "type": "multi_sound_single_meaning",
                "pinyin": "xiān",
                "rhyme_book": "《廣韻》虚嚴切，平嚴曉。",
                "meanings": []
            },
            {
                "type": "multi_sound_single_meaning",
                "pinyin": "kǎn",
                "rhyme_book": "《玉篇》音坎。",
                "meanings": [
                    "板"
                ]
            }
        ],
        "special_entries": []
    },
    {
        "character": "㸞",
        "variants": [],
        "synonyms": [],
        "definitions": [
            {
                "type": "single_sound_single_meaning",
                "pinyin": "zhé",
                "rhyme_book": "《改併四聲篇海》引",
                "meanings": [
                    "《川篇》音折",
                    "版"
                ]
            }
        ],
        "special_entries": []
    },
    {
        "character": "㸟",
        "variants": [],
        "synonyms": [],
        "definitions": [
            {
                "type": "single_sound_single_meaning",
                "pinyin": "zhī",
                "rhyme_book": "《改併四聲篇海》引",
                "meanings": [
                    "《川篇》章移切",
                    "盖合"
                ]
            }
        ],
        "special_entries": []
    },
    {
        "character": "㸠",
        "variants": [],
        "synonyms": [
            "𤕷"
        ],
        "definitions": [],
        "special_entries": []
    },
    {
        "character": "㸡",
        "variants": [],
        "synonyms": [],
        "definitions": [
            {
                "type": "single_sound_multi_meaning",
                "pinyin": "hū",
                "rhyme_book": "《廣韻》市朱切，平虞禪。",
                "meanings": [
                    "〔㸡𤗬〕挡水板",
                    "横木渡水"
                ]
            }
        ],
        "special_entries": []
    },
    {
        "character": "㸢",
        "variants": [],
        "synonyms": [],
        "definitions": [
            {
                "type": "single_sound_multi_meaning",
                "pinyin": "èi",
                "rhyme_book": "《廣韻》平祕切，去至並。",
                "meanings": [
                    "床上的横板",
                    "窗户",
                    "模"
                ]
            }
        ],
        "special_entries": []
    },
    {
        "character": "㸣",
        "variants": [],
        "synonyms": [
            "業"
        ],
        "definitions": [],
        "special_entries": []
    },
    {
        "character": "㸤",
        "variants": [],
        "synonyms": [],
        "definitions": [
            {
                "type": "single_sound_single_meaning",
                "pinyin": "㸤piàn",
                "rhyme_book": "《廣韻》普麵切，去霰滂。",
                "meanings": [
                    "皮革中断"
                ]
            }
        ],
        "special_entries": []
    },
    {
        "character": "㸥",
        "variants": [],
        "synonyms": [],
        "definitions": [
            {
                "type": "single_sound_multi_meaning",
                "pinyin": "hàn",
                "rhyme_book": "《廣韻》士懺切，去鑑崇。",
                "meanings": [
                    "版"
                ]
            }
        ],
        "special_entries": []
    },
    {
        "character": "片",
        "variants": [],
        "synonyms": [],
        "definitions": [
            {
                "type": "multi_sound_multi_meaning",
                "pinyin": "piàn",
                "rhyme_book": "《廣韻》普麵切，去霰滂。元部。",
                "meanings": [
                    "剖开；分开",
                    "单；两方中的一方",
                    "半边",
                    "泛指扁而薄的东西",
                    "花瓣",
                    "用刀横割成薄片",
                    "形容很少或很短",
                    "指较大地区内划分的较小地区",
                    "封建时代官吏向皇帝所呈奏章正折后面的附页",
                    "片茶",
                    "词学术语",
                    "量词"
                ]
            },
            {
                "type": "multi_sound_single_meaning",
                "pinyin": "piān",
                "rhyme_book": null,
                "meanings": [
                    "指有图像、景物或录有声音图像的片子"
                ]
            },
            {
                "type": "multi_sound_single_meaning",
                "pinyin": "pàn",
                "rhyme_book": "《集韻》普半切，去换滂。元部。",
                "meanings": []
            }
        ],
        "special_entries": []
    },
    {
        "character": "版",
        "variants": [],
        "synonyms": [],
        "definitions": [
            {
                "type": "single_sound_multi_meaning",
                "pinyin": "bǎn",
                "rhyme_book": "《廣韻》布綰切，上潸幫。元部。",
                "meanings": [
                    "木板",
                    "筑土墙用的夹板",
                    "古时书写用的木片，后也指书籍",
                    "名册；户籍",
                    "国家的图籍",
                    "古代官吏上朝用的笏",
                    "授予官职",
                    "古城墙计量单位",
                    "印刷板",
                    "印刷物的版本",
                    "报纸的一面",
                    "饼金，古代饼状的金属货币"
                ]
            }
        ],
        "special_entries": []
    },
    {
        "character": "牉",
        "variants": [],
        "synonyms": [],
        "definitions": [
            {
                "type": "single_sound_multi_meaning",
                "pinyin": "àn",
                "rhyme_book": "《廣韻》普半切，去换滂。元部。",
                "meanings": [
                    "半",
                    "分开，分为两半"
                ]
            }
        ],
        "special_entries": []
    },
    {
        "character": "牊",
        "variants": [],
        "synonyms": [],
        "definitions": [
            {
                "type": "single_sound_multi_meaning",
                "pinyin": "háo",
                "rhyme_book": "《玉篇》直遥切。",
                "meanings": [
                    "几",
                    "床的别名"
                ]
            }
        ],
        "special_entries": []
    },
    {
        "character": "牋",
        "variants": [],
        "synonyms": [
            "箋"
        ],
        "definitions": [],
        "special_entries": []
    },
    {
        "character": "牌",
        "variants": [],
        "synonyms": [],
        "definitions": [
            {
                "type": "single_sound_multi_meaning",
                "pinyin": "ái",
                "rhyme_book": "《廣韻》薄佳切，平佳並。又步皆切。",
                "meanings": [
                    "〔簧牌〕户籍",
                    "揭示或作标志用的板",
                    "商标",
                    "古时的凭证",
                    "古代一种下行公文的名称",
                    "*宋*末的一种铜铸货币",
                    "古代兵器“盾”的俗称",
                    "旧时丧礼所设的木主；置于厅堂或宗庙、寺庙、神龛中写着祖先或神仙名字的木板",
                    "词曲的调名",
                    "一种娱乐用品（旧时多用为赌具）",
                    "*元*代军队编制的基层单位",
                    "*元*代军中小头目“牌头”的简称"
                ]
            }
        ],
        "special_entries": []
    },
    {
        "character": "牍",
        "variants": [
            "“牘”"
        ],
        "synonyms": [],
        "definitions": [],
        "special_entries": []
    },
    {
        "character": "牎",
        "variants": [],
        "synonyms": [
            "囱（窗）"
        ],
        "definitions": [],
        "special_entries": []
    },
    {
        "character": "牏",
        "variants": [],
        "synonyms": [],
        "definitions": [
            {
                "type": "single_sound_multi_meaning",
                "pinyin": "yú",
                "rhyme_book": "《廣韻》羊朱切，平虞以。又度侯切，持遇切。侯部。",
                "meanings": [
                    "筑墙时用于两端的短板",
                    "门边像圭形的小洞",
                    "空；挖空",
                    "凿穿（墙壁）",
                    "受粪便的木桶、木槽",
                    "越过",
                    "度，过渡",
                    "超过",
                    "胜过",
                    "行",
                    "远",
                    "长",
                    "飘荡",
                    "疾行",
                    "淫逸",
                    "逍遥",
                    "〔跇踰〕兽走貌",
                    "〔𨄅窬〕深下"
                ]
            }
        ],
        "special_entries": []
    },
    {
        "character": "牐",
        "variants": [],
        "synonyms": [
            "閘"
        ],
        "definitions": [],
        "special_entries": []
    },
    {
        "character": "牑",
        "variants": [],
        "synonyms": [],
        "definitions": [
            {
                "type": "multi_sound_single_meaning",
                "pinyin": "biān",
                "rhyme_book": "《廣韻》布玄切，平先幫。元部。",
                "meanings": [
                    "床板；床箦"
                ]
            },
            {
                "type": "multi_sound_single_meaning",
                "pinyin": "miàn",
                "rhyme_book": "《集韻》䁕見切，去霰明。",
                "meanings": []
            }
        ],
        "special_entries": []
    },
    {
        "character": "牒",
        "variants": [],
        "synonyms": [],
        "definitions": [
            {
                "type": "single_sound_multi_meaning",
                "pinyin": "dié",
                "rhyme_book": "《廣韻》徒協切，入帖定。盍部。",
                "meanings": [
                    "古代书写用的木（竹）片",
                    "簿籍",
                    "谱牒",
                    "公文",
                    "诉状",
                    "神前的誓词",
                    "床板",
                    "叠布，即棉布",
                    "𡧽",
                    "姓"
                ]
            }
        ],
        "special_entries": []
    },
    {
        "character": "牓",
        "variants": [],
        "synonyms": [],
        "definitions": [
            {
                "type": "multi_sound_multi_meaning",
                "pinyin": "bǎng",
                "rhyme_book": "《廣韻》北朗切，上蕩幫。",
                "meanings": [
                    "损害",
                    "阻碍；妨碍",
                    "中止",
                    "俗称相克"
                ]
            },
            {
                "type": "multi_sound_multi_meaning",
                "pinyin": "pāng",
                "rhyme_book": "《集韻》鋪郎切，平唐滂。",
                "meanings": [
                    "纳鞋底的模具"
                ]
            }
        ],
        "special_entries": []
    },
    {
        "character": "牔",
        "variants": [],
        "synonyms": [],
        "definitions": [
            {
                "type": "single_sound_single_meaning",
                "pinyin": "bó",
                "rhyme_book": "《集韻》伯各切，入鐸幫。",
                "meanings": [
                    "屋端版"
                ]
            }
        ],
        "special_entries": []
    },
    {
        "character": "牕",
        "variants": [],
        "synonyms": [
            "囱（窗）"
        ],
        "definitions": [],
        "special_entries": []
    },
    {
        "character": "牖",
        "variants": [],
        "synonyms": [],
        "definitions": [
            {
                "type": "single_sound_multi_meaning",
                "pinyin": "yǒu",
                "rhyme_book": "《廣韻》與久切，上有以。幽部。",
                "meanings": [
                    "木窗",
                    "姓",
                    "引导；教导；劝导",
                    "引诱；诱惑",
                    "前导，在前面引路的人",
                    "感触；感动",
                    "美称之词"
                ]
            }
        ],
        "special_entries": []
    },
    {
        "character": "牘",
        "variants": [],
        "synonyms": [],
        "definitions": [
            {
                "type": "single_sound_multi_meaning",
                "pinyin": "dú",
                "rhyme_book": "《廣韻》徒谷切，入屋定。屋部。",
                "meanings": [
                    "古时写字的木片",
                    "书信",
                    "公文",
                    "书籍",
                    "古乐器名"
                ]
            }
        ],
        "special_entries": []
    },
    {
        "character": "𤖩",
        "variants": [],
        "synonyms": [
            "妝"
        ],
        "definitions": [],
        "special_entries": []
    },
    {
        "character": "𤖪",
        "variants": [],
        "synonyms": [],
        "definitions": [
            {
                "type": "single_sound_single_meaning",
                "pinyin": "yí",
                "rhyme_book": "《玉篇》余之切。",
                "meanings": [
                    "𤖪☀"
                ]
            }
        ],
        "special_entries": []
    },
    {
        "character": "𤖫",
        "variants": [],
        "synonyms": [
            "帆"
        ],
        "definitions": [],
        "special_entries": []
    },
    {
        "character": "𤖬",
        "variants": [],
        "synonyms": [],
        "definitions": [
            {
                "type": "single_sound_single_meaning",
                "pinyin": "qǔ",
                "rhyme_book": "《改併四聲篇海》引",
                "meanings": [
                    "《龍龕手鑑》七主切",
                    "迫"
                ]
            }
        ],
        "special_entries": []
    },
    {
        "character": "𤖭",
        "variants": [],
        "synonyms": [],
        "definitions": [
            {
                "type": "single_sound_single_meaning",
                "pinyin": "pán",
                "rhyme_book": "《集韻》步還切，平删並。",
                "meanings": [
                    "片"
                ]
            }
        ],
        "special_entries": []
    },
    {
        "character": "𤖮",
        "variants": [],
        "synonyms": [],
        "definitions": [
            {
                "type": "single_sound_single_meaning",
                "pinyin": "gōu",
                "rhyme_book": "《改併四聲篇海·片部》引",
                "meanings": [
                    "《搜真玉鏡》：“𤖮，音勾"
                ]
            }
        ],
        "special_entries": []
    },
    {
        "character": "𤖯",
        "variants": [],
        "synonyms": [
            "𤗏"
        ],
        "definitions": [],
        "special_entries": []
    },
    {
        "character": "𤖰",
        "variants": [
            "“叚”"
        ],
        "synonyms": [],
        "definitions": [],
        "special_entries": []
    },
    {
        "character": "𤖱",
        "variants": [],
        "synonyms": [],
        "definitions": [
            {
                "type": "single_sound_single_meaning",
                "pinyin": "hé",
                "rhyme_book": "《廣韻》户戈切，平戈匣。",
                "meanings": [
                    "棺当，即棺材两头的木板"
                ]
            }
        ],
        "special_entries": []
    },
    {
        "character": "𤖲",
        "variants": [],
        "synonyms": [
            "枯"
        ],
        "definitions": [],
        "special_entries": []
    },
    {
        "character": "𤖳",
        "variants": [],
        "synonyms": [],
        "definitions": [
            {
                "type": "single_sound_single_meaning",
                "pinyin": "pèng",
                "rhyme_book": "《集韻》叵迸切，去諍滂。",
                "meanings": [
                    "析木声"
                ]
            }
        ],
        "special_entries": []
    },
    {
        "character": "𤖴",
        "variants": [],
        "synonyms": [
            "坼"
        ],
        "definitions": [],
        "special_entries": []
    },
    {
        "character": "𤖵",
        "variants": [],
        "synonyms": [],
        "definitions": [
            {
                "type": "single_sound_single_meaning",
                "pinyin": "jù",
                "rhyme_book": "《改併四聲篇海·片部》引",
                "meanings": [
                    "《搜真玉鏡》：“𤖵，音句"
                ]
            }
        ],
        "special_entries": []
    },
    {
        "character": "𤖷",
        "variants": [
            "“㿭”"
        ],
        "synonyms": [],
        "definitions": [],
        "special_entries": []
    },
    {
        "character": "𤖺",
        "variants": [],
        "synonyms": [],
        "definitions": [
            {
                "type": "single_sound_single_meaning",
                "pinyin": "liè",
                "rhyme_book": "《集韻》力蘖切，入薛來。",
                "meanings": [
                    "剖"
                ]
            }
        ],
        "special_entries": []
    },
    {
        "character": "𤖻",
        "variants": [],
        "synonyms": [],
        "definitions": [
            {
                "type": "single_sound_single_meaning",
                "pinyin": "shì",
                "rhyme_book": "《廣韻》施智切，去寘書。又渠遥切。",
                "meanings": [
                    "几"
                ]
            }
        ],
        "special_entries": []
    },
    {
        "character": "𤖼",
        "variants": [],
        "synonyms": [],
        "definitions": [
            {
                "type": "single_sound_single_meaning",
                "pinyin": "pò",
                "rhyme_book": "《廣韻》普伯切，入陌滂。",
                "meanings": [
                    "将物体剖开"
                ]
            }
        ],
        "special_entries": []
    },
    {
        "character": "𤖽",
        "variants": [],
        "synonyms": [
            "向"
        ],
        "definitions": [],
        "special_entries": []
    },
    {
        "character": "𤖾",
        "variants": [],
        "synonyms": [
            "𤖽",
            "𤖽"
        ],
        "definitions": [],
        "special_entries": []
    },
    {
        "character": "𤖿",
        "variants": [],
        "synonyms": [
            "𤗚（𤖼）",
            "𤗚"
        ],
        "definitions": [],
        "special_entries": []
    },
    {
        "character": "𤗀",
        "variants": [],
        "synonyms": [],
        "definitions": [
            {
                "type": "single_sound_single_meaning",
                "pinyin": "luǒ",
                "rhyme_book": "《玉篇》力可切。",
                "meanings": [
                    "艣的别名"
                ]
            }
        ],
        "special_entries": []
    },
    {
        "character": "𤗁",
        "variants": [],
        "synonyms": [],
        "definitions": [
            {
                "type": "single_sound_single_meaning",
                "pinyin": "cù",
                "rhyme_book": "《廣韻》七玉切，入燭清。",
                "meanings": [
                    "迫"
                ]
            }
        ],
        "special_entries": []
    },
    {
        "character": "𤗂",
        "variants": [],
        "synonyms": [
            "𤗂"
        ],
        "definitions": [],
        "special_entries": []
    },
    {
        "character": "𤗃",
        "variants": [],
        "synonyms": [],
        "definitions": [
            {
                "type": "single_sound_single_meaning",
                "pinyin": "yǔ",
                "rhyme_book": "《改併四聲篇海·片部》引",
                "meanings": [
                    "《搜真玉鏡》：“𤗃，羊父切"
                ]
            }
        ],
        "special_entries": []
    },
    {
        "character": "𤗄",
        "variants": [],
        "synonyms": [
            "牕"
        ],
        "definitions": [],
        "special_entries": []
    },
    {
        "character": "𤗅",
        "variants": [],
        "synonyms": [
            "胤"
        ],
        "definitions": [],
        "special_entries": []
    },
    {
        "character": "𤗇",
        "variants": [],
        "synonyms": [],
        "definitions": [
            {
                "type": "single_sound_single_meaning",
                "pinyin": "kòng",
                "rhyme_book": "《廣韻》苦貢切，去送溪。",
                "meanings": [
                    "穿垣"
                ]
            }
        ],
        "special_entries": []
    },
    {
        "character": "𤗈",
        "variants": [],
        "synonyms": [],
        "definitions": [
            {
                "type": "single_sound_multi_meaning",
                "pinyin": "iè",
                "rhyme_book": "《廣韻》蘇協切，入帖心。",
                "meanings": [
                    "〔𤗈牒〕小楔",
                    "简"
                ]
            }
        ],
        "special_entries": []
    },
    {
        "character": "𤗉",
        "variants": [],
        "synonyms": [
            "牎（窗）"
        ],
        "definitions": [],
        "special_entries": []
    },
    {
        "character": "𤗊",
        "variants": [],
        "synonyms": [
            "牒",
            "牒"
        ],
        "definitions": [],
        "special_entries": []
    },
    {
        "character": "𤗋",
        "variants": [],
        "synonyms": [
            "牌"
        ],
        "definitions": [],
        "special_entries": []
    },
    {
        "character": "𤗌",
        "variants": [],
        "synonyms": [
            "㸢",
            "㸢"
        ],
        "definitions": [],
        "special_entries": []
    },
    {
        "character": "𤗍",
        "variants": [],
        "synonyms": [],
        "definitions": [
            {
                "type": "single_sound_single_meaning",
                "pinyin": "wǎn",
                "rhyme_book": "《廣韻》於阮切，上阮影。",
                "meanings": [
                    "船𤗍木"
                ]
            }
        ],
        "special_entries": []
    },
    {
        "character": "𤗎",
        "variants": [],
        "synonyms": [],
        "definitions": [
            {
                "type": "single_sound_multi_meaning",
                "pinyin": "ǎn",
                "rhyme_book": "《廣韻》衣儉切，上琰影。",
                "meanings": [
                    "屋檐耑版",
                    "户坏"
                ]
            }
        ],
        "special_entries": []
    },
    {
        "character": "𤗏",
        "variants": [],
        "synonyms": [],
        "definitions": [
            {
                "type": "single_sound_single_meaning",
                "pinyin": "péi",
                "rhyme_book": "《廣韻》薄回切，平灰並。又扶來切。",
                "meanings": [
                    "踏版"
                ]
            }
        ],
        "special_entries": []
    },
    {
        "character": "𤗒",
        "variants": [],
        "synonyms": [
            "牓"
        ],
        "definitions": [],
        "special_entries": []
    },
    {
        "character": "𤗓",
        "variants": [],
        "synonyms": [],
        "definitions": [
            {
                "type": "single_sound_single_meaning",
                "pinyin": "chéng",
                "rhyme_book": "《改併四聲篇海·片部》引",
                "meanings": [
                    "《奚韻》：“𤗓，音承"
                ]
            }
        ],
        "special_entries": []
    },
    {
        "character": "𤗔",
        "variants": [],
        "synonyms": [
            "新"
        ],
        "definitions": [],
        "special_entries": []
    },
    {
        "character": "𤗕",
        "variants": [],
        "synonyms": [
            "𤗭",
            "𤗭"
        ],
        "definitions": [],
        "special_entries": []
    },
    {
        "character": "𤗗",
        "variants": [],
        "synonyms": [
            "棟",
            "𤗛"
        ],
        "definitions": [],
        "special_entries": []
    },
    {
        "character": "𤗘",
        "variants": [],
        "synonyms": [],
        "definitions": [
            {
                "type": "single_sound_single_meaning",
                "pinyin": "tí",
                "rhyme_book": "《集韻》田黎切，平齊定。",
                "meanings": [
                    "墙壁一方丈"
                ]
            }
        ],
        "special_entries": []
    },
    {
        "character": "𤗙",
        "variants": [],
        "synonyms": [],
        "definitions": [
            {
                "type": "multi_sound_single_meaning",
                "pinyin": "chè",
                "rhyme_book": "《集韻》耻格切，入陌徹。",
                "meanings": []
            },
            {
                "type": "multi_sound_single_meaning",
                "pinyin": "tuò",
                "rhyme_book": "《集韻》闥各切，入鐸透。",
                "meanings": []
            }
        ],
        "special_entries": []
    },
    {
        "character": "𤗚",
        "variants": [],
        "synonyms": [],
        "definitions": [
            {
                "type": "single_sound_multi_meaning",
                "pinyin": "bì",
                "rhyme_book": "《廣韻》符逼切（",
                "meanings": [
                    "薄版"
                ]
            }
        ],
        "special_entries": []
    },
    {
        "character": "𤗛",
        "variants": [],
        "synonyms": [],
        "definitions": [
            {
                "type": "single_sound_single_meaning",
                "pinyin": "liàn",
                "rhyme_book": "《廣韻》郎甸切，去霰來。",
                "meanings": [
                    "木板的纹理"
                ]
            }
        ],
        "special_entries": []
    },
    {
        "character": "𤗜",
        "variants": [
            "姓。《篇海類編·宫室類·片部》：“𤗜，人姓。”一说“假”"
        ],
        "synonyms": [],
        "definitions": [],
        "special_entries": []
    },
    {
        "character": "𤗞",
        "variants": [],
        "synonyms": [],
        "definitions": [
            {
                "type": "single_sound_single_meaning",
                "pinyin": "tíng",
                "rhyme_book": "《龍龕手鑑》音亭。",
                "meanings": [
                    "亭榭"
                ]
            }
        ],
        "special_entries": []
    },
    {
        "character": "𤗟",
        "variants": [],
        "synonyms": [
            "新"
        ],
        "definitions": [],
        "special_entries": []
    },
    {
        "character": "𤗠",
        "variants": [],
        "synonyms": [
            "牐"
        ],
        "definitions": [],
        "special_entries": []
    },
    {
        "character": "𤗢",
        "variants": [],
        "synonyms": [],
        "definitions": [
            {
                "type": "single_sound_single_meaning",
                "pinyin": "tī",
                "rhyme_book": "《集韻》天黎切，平齊透。",
                "meanings": [
                    "牌"
                ]
            }
        ],
        "special_entries": []
    },
    {
        "character": "𤗣",
        "variants": [],
        "synonyms": [
            "牒"
        ],
        "definitions": [],
        "special_entries": []
    },
    {
        "character": "𤗥",
        "variants": [],
        "synonyms": [
            "㸣"
        ],
        "definitions": [],
        "special_entries": []
    },
    {
        "character": "𤗦",
        "variants": [],
        "synonyms": [
            "隔"
        ],
        "definitions": [],
        "special_entries": []
    },
    {
        "character": "𤗨",
        "variants": [],
        "synonyms": [],
        "definitions": [
            {
                "type": "single_sound_single_meaning",
                "pinyin": "dié",
                "rhyme_book": "《廣韻》徒協切，入帖定。",
                "meanings": [
                    "治"
                ]
            }
        ],
        "special_entries": []
    },
    {
        "character": "𤗩",
        "variants": [],
        "synonyms": [
            "㸢"
        ],
        "definitions": [],
        "special_entries": []
    },
    {
        "character": "𤗪",
        "variants": [],
        "synonyms": [],
        "definitions": [
            {
                "type": "single_sound_single_meaning",
                "pinyin": "shù",
                "rhyme_book": "《集韻》朔律切，入術生。",
                "meanings": [
                    "板"
                ]
            }
        ],
        "special_entries": []
    },
    {
        "character": "𤗫",
        "variants": [],
        "synonyms": [],
        "definitions": [
            {
                "type": "single_sound_single_meaning",
                "pinyin": "lí",
                "rhyme_book": "《集韻》鄰知切，平支來。",
                "meanings": [
                    "破木"
                ]
            }
        ],
        "special_entries": []
    },
    {
        "character": "𤗬",
        "variants": [],
        "synonyms": [],
        "definitions": [
            {
                "type": "single_sound_single_meaning",
                "pinyin": "lǘ",
                "rhyme_book": "《廣韻》力朱切，平虞來。",
                "meanings": [
                    "〔㸡𤗬〕见“㸡”"
                ]
            }
        ],
        "special_entries": []
    },
    {
        "character": "𤗭",
        "variants": [],
        "synonyms": [],
        "definitions": [
            {
                "type": "single_sound_multi_meaning",
                "pinyin": "ià",
                "rhyme_book": "《集韻》虚訝切，去禡曉。",
                "meanings": [
                    "古地名"
                ]
            }
        ],
        "special_entries": []
    },
    {
        "character": "𤗮",
        "variants": [],
        "synonyms": [
            "牐（閘）"
        ],
        "definitions": [],
        "special_entries": []
    },
    {
        "character": "𤗯",
        "variants": [],
        "synonyms": [],
        "definitions": [
            {
                "type": "single_sound_single_meaning",
                "pinyin": "cuī",
                "rhyme_book": "《廣韻》素回切，平灰心。又",
                "meanings": [
                    "《集韻》倉回切",
                    "〔𤗯𤗴〕也作“𨻵隤”"
                ]
            }
        ],
        "special_entries": []
    },
    {
        "character": "𤗱",
        "variants": [],
        "synonyms": [
            "牖"
        ],
        "definitions": [],
        "special_entries": []
    },
    {
        "character": "𤗳",
        "variants": [],
        "synonyms": [],
        "definitions": [
            {
                "type": "single_sound_single_meaning",
                "pinyin": "bō",
                "rhyme_book": "《篇海類編》補各切。",
                "meanings": [
                    "挡风板"
                ]
            }
        ],
        "special_entries": []
    },
    {
        "character": "𤗴",
        "variants": [],
        "synonyms": [],
        "definitions": [
            {
                "type": "single_sound_single_meaning",
                "pinyin": "tuí",
                "rhyme_book": "《廣韻》杜回切，平灰定。",
                "meanings": [
                    "〔𤗯𤗴〕见“𤗯”"
                ]
            }
        ],
        "special_entries": []
    },
    {
        "character": "𤗵",
        "variants": [],
        "synonyms": [],
        "definitions": [
            {
                "type": "single_sound_single_meaning",
                "pinyin": "pú",
                "rhyme_book": "《集韻》博木切，入屋幫。",
                "meanings": [
                    "大墙板"
                ]
            }
        ],
        "special_entries": []
    },
    {
        "character": "𤗶",
        "variants": [],
        "synonyms": [
            "𤖖"
        ],
        "definitions": [],
        "special_entries": []
    },
    {
        "character": "𤗷",
        "variants": [],
        "synonyms": [
            "棱"
        ],
        "definitions": [],
        "special_entries": []
    },
    {
        "character": "𤗸",
        "variants": [],
        "synonyms": [],
        "definitions": [
            {
                "type": "multi_sound_single_meaning",
                "pinyin": "fèn",
                "rhyme_book": "《玉篇》扶忿切。",
                "meanings": [
                    "床板"
                ]
            },
            {
                "type": "multi_sound_single_meaning",
                "pinyin": "fén",
                "rhyme_book": "《類篇》符分切，平文奉。",
                "meanings": [
                    "〔𤗸𤗂〕器足"
                ]
            }
        ],
        "special_entries": []
    },
    {
        "character": "𤗺",
        "variants": [],
        "synonyms": [],
        "definitions": [
            {
                "type": "single_sound_single_meaning",
                "pinyin": "bó",
                "rhyme_book": "《廣韻》博厄切，入麥幫。",
                "meanings": [
                    "小而硬的豆"
                ]
            }
        ],
        "special_entries": []
    },
    {
        "character": "𤗻",
        "variants": [],
        "synonyms": [],
        "definitions": [
            {
                "type": "single_sound_single_meaning",
                "pinyin": "chàn",
                "rhyme_book": "《集韻》昌豔切，去豔昌。",
                "meanings": [
                    "屋檐端板"
                ]
            }
        ],
        "special_entries": []
    },
    {
        "character": "𤗾",
        "variants": [],
        "synonyms": [],
        "definitions": [
            {
                "type": "single_sound_single_meaning",
                "pinyin": "dāng",
                "rhyme_book": "《龍龕手鑑·片部》：“𤗾，音當。”",
                "meanings": [
                    "《字彙補·片部》：“𤗾，見《金鏡》"
                ]
            }
        ],
        "special_entries": []
    },
    {
        "character": "𤗿",
        "variants": [],
        "synonyms": [],
        "definitions": [
            {
                "type": "single_sound_single_meaning",
                "pinyin": "tǎi",
                "rhyme_book": "《集韻》坦亥切，上海透。",
                "meanings": [
                    "从下端向上削木"
                ]
            }
        ],
        "special_entries": []
    },
    {
        "character": "𤘀",
        "variants": [],
        "synonyms": [
            "檮"
        ],
        "definitions": [],
        "special_entries": []
    },
    {
        "character": "𤘃",
        "variants": [],
        "synonyms": [],
        "definitions": [
            {
                "type": "single_sound_single_meaning",
                "pinyin": "lì",
                "rhyme_book": "《集韻》狼狄切，入錫來",
                "meanings": []
            }
        ],
        "special_entries": []
    }
]